{
 "caches": {
  "next-apps-docs": {
   "directory": "/app/apps/docs/.next/cache",
   "type": "shared"
  },
  "next-apps-web": {
   "directory": "/app/apps/web/.next/cache",
   "type": "shared"
  },
  "node-modules": {
   "directory": "/app/node_modules/.cache",
   "type": "shared"
  },
  "npm-install": {
   "directory": "/root/.npm",
   "type": "shared"
  }
 },
 "deploy": {
  "inputs": [
   {
    "image": "ghcr.io/railwayapp/railpack-runtime:latest"
   },
   {
    "include": [
     "/mise/shims",
     "/mise/installs",
     "/usr/local/bin/mise",
     "/etc/mise/config.toml",
     "/root/.local/state/mise"
    ],
    "step": "packages:mise"
   },
   {
    "include": [
     "/app/node_modules"
    ],
    "step": "build"
   },
   {
    "exclude": [
     "node_modules",
     ".yarn"
    ],
    "include": [
     "/root/.cache",
     ".",
     "/opt/corepack"
    ],
    "step": "build"
   }
  ],
  "variables": {
   "CI": "true",
   "NODE_ENV": "production",
   "NPM_CONFIG_FUND": "false",
   "NPM_CONFIG_PRODUCTION": "false",
   "NPM_CONFIG_UPDATE_NOTIFIER": "false"
  }
 },
 "steps": [
  {
   "assets": {
    "mise.toml": "[mise.toml]"
   },
   "commands": [
    {
     "path": "/mise/shims"
    },
    {
     "customName": "create mise config",
     "name": "mise.toml",
     "path": "/etc/mise/config.toml"
    },
    {
     "cmd": "sh -c 'mise trust -a \u0026\u0026 mise install'",
     "customName": "install mise packages: node"
    }
   ],
   "inputs": [
    {
     "image": "ghcr.io/railwayapp/railpack-builder:latest"
    }
   ],
   "name": "packages:mise",
   "variables": {
    "MISE_CACHE_DIR": "/mise/cache",
    "MISE_CONFIG_DIR": "/mise",
    "MISE_DATA_DIR": "/mise",
    "MISE_INSTALLS_DIR": "/mise/installs",
    "MISE_NODE_COREPACK": "true",
    "MISE_SHIMS_DIR": "/mise/shims"
   }
  },
  {
   "caches": [
    "npm-install"
   ],
   "commands": [
    {
     "path": "/app/node_modules/.bin"
    },
    {
     "dest": "package.json",
     "src": "package.json"
    },
    {
     "cmd": "sh -c 'npm i -g corepack@latest \u0026\u0026 corepack enable \u0026\u0026 corepack prepare --activate'",
     "customName": "npm i -g corepack@latest \u0026\u0026 corepack enable \u0026\u0026 corepack prepare --activate"
    },
    {
     "dest": "package.json",
     "src": "package.json"
    },
    {
     "dest": "apps/docs/package.json",
     "src": "apps/docs/package.json"
    },
    {
     "dest": "apps/web/package.json",
     "src": "apps/web/package.json"
    },
    {
     "dest": "packages/eslint-config/package.json",
     "src": "packages/eslint-config/package.json"
    },
    {
     "dest": "packages/typescript-config/package.json",
     "src": "packages/typescript-config/package.json"
    },
    {
     "dest": "packages/ui/package.json",
     "src": "packages/ui/package.json"
    },
    {
     "dest": "package-lock.json",
     "src": "package-lock.json"
    },
    {
     "dest": ".npmrc",
     "src": ".npmrc"
    },
    {
     "cmd": "npm ci"
    }
   ],
   "inputs": [
    {
     "step": "packages:mise"
    }
   ],
   "name": "install",
   "variables": {
    "CI": "true",
    "COREPACK_HOME": "/opt/corepack",
    "NODE_ENV": "production",
    "NPM_CONFIG_FUND": "false",
    "NPM_CONFIG_PRODUCTION": "false",
    "NPM_CONFIG_UPDATE_NOTIFIER": "false"
   }
  },
  {
   "inputs": [
    {
     "step": "install"
    }
   ],
   "name": "prune"
  },
  {
   "caches": [
    "node-modules",
    "next-apps-docs",
    "next-apps-web"
   ],
   "commands": [
    {
     "dest": ".",
     "src": "."
    },
    {
     "cmd": "npm run build"
    }
   ],
   "inputs": [
    {
     "step": "install"
    }
   ],
   "name": "build",
   "secrets": [
    "*"
   ]
  }
 ]
}